openedx_ledger/__init__.py
openedx_ledger/admin.py
openedx_ledger/api.py
openedx_ledger/apps.py
openedx_ledger/constants.py
openedx_ledger/models.py
openedx_ledger/urls.py
openedx_ledger/utils.py
openedx_ledger/views.py
openedx_ledger/migrations/0001_initial.py
openedx_ledger/migrations/0002_historicalledger_historicalreversal_historicaltransaction.py
openedx_ledger/migrations/0003_field_updates_20230216_1605.py
openedx_ledger/migrations/0004_ledger_idpkey_blankable.py
openedx_ledger/migrations/0005_help_text_and_more_indices.py
openedx_ledger/migrations/0006_auto_20230404_1744.py
openedx_ledger/migrations/0007_alter_externalfulfillmentprovider_name.py
openedx_ledger/migrations/0008_adjustment_model.py
openedx_ledger/migrations/0009_add_email_and_title_to_transactions.py
openedx_ledger/migrations/0010_transaction_parent_content_key.py
openedx_ledger/migrations/0011_deposit_models.py
openedx_ledger/migrations/0012_optional_deposit_sales_contract_reference.py
openedx_ledger/migrations/0013_alter_historicaladjustment_options_and_more.py
openedx_ledger/migrations/0014_rename_transaction_ledger_content_key_openedx_led_ledger__4c90f0_idx_and_more.py
openedx_ledger/migrations/0015_add_course_run_start_date_to_transaction.py
openedx_ledger/migrations/__init__.py
openedx_ledger/signals/__init__.py
openedx_ledger/signals/signals.py
openedx_ledger/templates/edx_ledger/base.html
openedx_ledger/templates/edx_ledger/admin/reverse_transaction.html
openedx_ledger/test_utils/__init__.py
openedx_ledger/test_utils/factories.py
openedx_ledger-1.6.9.dist-info/licenses/LICENSE.txt
openedx_ledger-1.6.9.dist-info/METADATA
openedx_ledger-1.6.9.dist-info/WHEEL
openedx_ledger-1.6.9.dist-info/top_level.txt
openedx_ledger-1.6.9.dist-info/RECORD
