Metadata-Version: 2.4
Name: openedx-ledger
Version: 1.6.9
Summary: Records transactions against a ledger, denominated in units of value.
Home-page: https://github.com/openedx/openedx-ledger
Author: edX
Author-email: oscm@edx.org
License: AGPL 3.0
Keywords: Python edx
Classifier: Development Status :: 3 - Alpha
Classifier: Framework :: Django
Classifier: Framework :: Django :: 4.2
Classifier: Framework :: Django :: 5.2
Classifier: Intended Audience :: Developers
Classifier: License :: OSI Approved :: GNU Affero General Public License v3 or later (AGPLv3+)
Classifier: Natural Language :: English
Classifier: Programming Language :: Python :: 3
Classifier: Programming Language :: Python :: 3.12
Requires-Python: >=3.12
License-File: LICENSE.txt
Requires-Dist: Django
Requires-Dist: django-extensions
Requires-Dist: django-filter
Requires-Dist: django-object-actions
Requires-Dist: django-simple-history
Requires-Dist: djangoql
Requires-Dist: edx-django-release-util
Requires-Dist: edx-django-utils
Requires-Dist: edx-rbac
Requires-Dist: jsonfield2
Requires-Dist: mysqlclient
Requires-Dist: openedx-events
Requires-Dist: pytz
Requires-Dist: redis
Requires-Dist: rules
Dynamic: author
Dynamic: author-email
Dynamic: classifier
Dynamic: description
Dynamic: home-page
Dynamic: keywords
Dynamic: license
Dynamic: license-file
Dynamic: requires-dist
Dynamic: requires-python
Dynamic: summary
